[
  {
    "id": 1,
    "name": "Jan",
    "lastName": "Kowalski"
  },
  {
    "id": 2,
    "name": "Anna",
    "lastName": "Nowak"
  },
  {
    "id": 3,
    "name": "Tomasz",
    "lastName": "Janicki"
  },
  {
    "id": 4,
    "name": "Ewa",
    "lastName": "Nosal"
  },
  {
    "name": "Maciej",
    "lastName": "Zieliński",
    "id": 5
  },
  {
    "name": "Marzena",
    "lastName": "Zul",
    "id": 6
  },
  {
    "name": "Artur",
    "lastName": "Krud",
    "id": 7
  },
  {
    "name": "Łukasz",
    "lastName": "Zieba",
    "id": 8
  },
  {
    "name": "Ludwik",
    "lastName": "Nowak",
    "id": 9
  },
  {
    "name": "Patrycja",
    "lastName": "Woźniak",
    "id": 10
  },
  {
    "name": "Euzebiusz",
    "lastName": "Smolarek",
    "id": 11
  },
  {
    "name": "Staszek",
    "lastName": "Szaszłyk",
    "id": 12
  },
  {
    "name": "Gerard",
    "lastName": "Doktor",
    "id": 13
  },
  {
    "name": "Mikołaj",
    "lastName": "Święty",
    "id": 14
  },
  {
    "name": "Robert",
    "lastName": "Kowalski",
    "id": 15
  },
  {
    "name": "Ignacy",
    "lastName": "Łukasiewicz",
    "id": 16
  },
  {
    "name": "Niles",
    "lastName": "Bohr",
    "id": 17
  },
  {
    "name": "Bjorn",
    "lastName": "Żelaznoboki",
    "id": 18
  },
  {
    "name": "Ragnar",
    "lastName": "Lodbrok",
    "id": 19
  },
  {
    "name": "Rumcajs",
    "lastName": "Brodaty",
    "id": 20
  },
  {
    "name": "Gandalf",
    "lastName": "Szary",
    "id": 21
  },
  {
    "name": "Papa",
    "lastName": "Smerf",
    "id": 22
  },
  {
    "name": "Lucyfer",
    "lastName": "Morningstar",
    "id": 23
  },
  {
    "name": "Huba",
    "lastName": "Buba",
    "id": 24
  }
]
